mcp_fmi/__init__.py
mcp_fmi/artifacts.py
mcp_fmi/inputs.py
mcp_fmi/schema.py
mcp_fmi/server.py
mcp_fmi/simulation.py
mcp_fmi-0.1.7.dist-info/licenses/LICENSE
mcp_fmi-0.1.7.dist-info/METADATA
mcp_fmi-0.1.7.dist-info/WHEEL
mcp_fmi-0.1.7.dist-info/entry_points.txt
mcp_fmi-0.1.7.dist-info/top_level.txt
mcp_fmi-0.1.7.dist-info/RECORD
