Metadata-Version: 2.4
Name: mcp-fmi
Version: 0.1.7
Summary: Unofficial integration of fmpy with mcp.
Requires-Python: >=3.11
License-File: LICENSE
Requires-Dist: dash>=3.0.4
Requires-Dist: mcp[cli]>=1.9.0
Requires-Dist: python-dotenv>=1.1.0
Requires-Dist: fmpy
Requires-Dist: numpy
Requires-Dist: pydantic
Provides-Extra: dev
Requires-Dist: pytest>=8.3.5; extra == "dev"
Requires-Dist: pytest-asyncio>=0.26.0; extra == "dev"
Requires-Dist: build; extra == "dev"
Requires-Dist: twine; extra == "dev"
Requires-Dist: hatch; extra == "dev"
Dynamic: license-file
